rounders/__init__.py
rounders/decimal_overloads.py
rounders/float_overloads.py
rounders/format.py
rounders/fraction_overloads.py
rounders/generics.py
rounders/int_overloads.py
rounders/intermediate.py
rounders/mode_specific.py
rounders/modes.py
rounders/py.typed
rounders/round_to.py
rounders/test/__init__.py
rounders/test/test_format.py
rounders/test/test_round.py
rounders-0.2.0.dist-info/LICENSE
rounders-0.2.0.dist-info/METADATA
rounders-0.2.0.dist-info/WHEEL
rounders-0.2.0.dist-info/top_level.txt
rounders-0.2.0.dist-info/RECORD
