Metadata-Version: 2.1
Name: rounders
Version: 0.2.0
Summary: round-function equivalents with different rounding-modes
Author-email: Mark Dickinson <dickinsm@gmail.com>
Project-URL: source, https://github.com/mdickinson/rounders
Keywords: round,rounding,significant figures,decimal places,rounding mode
Classifier: License :: OSI Approved :: Apache Software License
Classifier: Operating System :: OS Independent
Classifier: Programming Language :: Python :: 3
Classifier: Topic :: Scientific/Engineering :: Mathematics
Requires-Python: >=3.8
License-File: LICENSE
